CHANGES.txt
MANIFEST.in
README.rst
setup.cfg
setup.py
tox.ini
pyramid_macauth/__init__.py
pyramid_macauth/tests.py
pyramid_macauth.egg-info/PKG-INFO
pyramid_macauth.egg-info/SOURCES.txt
pyramid_macauth.egg-info/dependency_links.txt
pyramid_macauth.egg-info/not-zip-safe
pyramid_macauth.egg-info/requires.txt
pyramid_macauth.egg-info/top_level.txt