Metadata-Version: 1.1
Name: pyramid-macauth
Version: 0.3.0
Summary: pyramid_macauth
Home-page: https://github.com/mozilla-services/pyramid_macauth
Author: Mozilla Services
Author-email: services-dev@mozilla.org
License: MPLv2.0
Keywords: authentication token MAC
Platform: UNKNOWN
Classifier: Programming Language :: Python
Classifier: License :: OSI Approved :: Mozilla Public License 2.0 (MPL 2.0)
